{
  "external_urls" : {
    "spotify" : "https://open.spotify.com/artist/4tIKaxUmpXzshok2yCnwdf"
  },
  "followers" : {
    "href" : null,
    "total" : 500786
  },
  "genres" : [ "afrobeats", "ghanaian alternative", "ghanaian pop" ],
  "href" : "https://api.spotify.com/v1/artists/4tIKaxUmpXzshok2yCnwdf",
  "id" : "4tIKaxUmpXzshok2yCnwdf",
  "images" : [ {
    "height" : 640,
    "url" : "https://i.scdn.co/image/ab6761610000e5ebdec26b330e90ddcf3d570fa1",
    "width" : 640
  }, {
    "height" : 320,
    "url" : "https://i.scdn.co/image/ab67616100005174dec26b330e90ddcf3d570fa1",
    "width" : 320
  }, {
    "height" : 160,
    "url" : "https://i.scdn.co/image/ab6761610000f178dec26b330e90ddcf3d570fa1",
    "width" : 160
  } ],
  "name" : "King Promise",
  "popularity" : 62,
  "type" : "artist",
  "uri" : "spotify:artist:4tIKaxUmpXzshok2yCnwdf"
}